zhiqing/__init__.py
zhiqing-0.0.8.dist-info/licenses/LICENSE
zhiqing-0.0.8.dist-info/METADATA
zhiqing-0.0.8.dist-info/WHEEL
zhiqing-0.0.8.dist-info/top_level.txt
zhiqing-0.0.8.dist-info/RECORD
