Metadata-Version: 2.4
Name: zhiqing
Version: 0.0.8
Summary: Zhiqing's Module
Author-email: Zhiqing Xiao <xzq.xiaozhiqing@gmail.com>
Project-URL: Homepage, http://github.com/zhiqingxiao/
Classifier: Programming Language :: Python
License-File: LICENSE
Requires-Dist: importlib-metadata
Provides-Extra: test
Requires-Dist: pytest; extra == "test"
Dynamic: license-file
